Workbook

Sheet Summary
A1: ASTRA: hosting options and costs
A2: Prepared for Prof. Haris Mouratidis, University of Essex (IADS). Prices checked on 27 October 2026.
A4: Purpose | B4: Specific online services that could host ASTRA, with the monthly cost of each, for (1) a shared test, (2) a pilot with a managed database, and (3) a small production set-up.
A5: What ASTRA needs | B5: A Linux server that runs Docker Compose: three containers (web studio, API, PostgreSQL 16). From the repository's deployment guide (deploy/DEPLOY.md): Docker Engine with Compose v2.20 or later, about 4 GB RAM, about 5 GB disk, no GPU. For production, HTTPS in front (free with Let's Encrypt and Caddy), backups, and a database that is not exposed to the internet.
A6: How to read the prices | B6: Green cells: read on the provider's own pricing page on 27 Oct 2026. Amber cells: from third-party pricing sites that disagree with each other or could not be checked against the provider: treat as indicative and confirm before ordering. Red cells: the provider does not publish a price for the spec; a quote is needed. Currencies are as the provider quotes them (USD, EUR or GBP); the Scenarios sheet converts using rates you can edit.
A7: Taxes | B7: Provider prices are normally shown excluding VAT. The Scenarios sheet adds UK VAT at a rate you can change.
A8: Main finding | B8: A single 4 GB server (about USD 24 a month at DigitalOcean or Amazon Lightsail, both verified, both with a London region) is enough for a shared test. Adding a managed PostgreSQL database for a pilot costs about USD 54 a month at Lightsail (verified) and about USD 85 at DigitalOcean or Azure (database figure unverified). Cheapest verified EU options are Scaleway (about EUR 17 a month, Paris) and Hetzner (EUR 19.99, Germany or Finland, but Hetzner's page showed the plans as currently unavailable when checked). Hetzner and Scaleway have no UK data centre. For UK data residency use DigitalOcean London, Lightsail London, Azure UK South or Mythic Beasts (quote).
A9: Not verified (important) | B9: Region-specific prices (London) for DigitalOcean and Lightsail were not separately checked; list prices were read from the global pricing page. Azure and managed-database figures marked amber come from third-party sites. Exchange rates on the Scenarios sheet are placeholders. Always confirm in the provider's own calculator before committing.
A10: What is not in these figures | B10: Domain name, backups and snapshot storage, outbound traffic beyond the allowance, monitoring and log storage, staff time to run and patch the server, and an independent security test. See the Other costs sheet.
A11: Sheets | B11: Requirements (sizing), Options (every service with price and source), Scenarios (monthly totals, editable rates), Other costs, Sources.

Sheet Requirements
A1: Item | B1: Shared test | C1: Pilot | D1: Small production | E1: Basis
A2: Servers (Docker host) | B2: 1 | C2: 1 | D2: 1 to 2 (second for staging) | E2: ASTRA is single-organisation per instance; one Compose stack per customer.
A3: RAM | B3: 4 GB | C3: 4 GB | D3: 8 GB | E3: Repository guide says about 4 GB. The 8 GB for production is my sizing assumption for headroom with more monitors and users; not measured.
A4: vCPU | B4: 2 | C4: 2 | D4: 2 to 4 | E4: Assumption: the API is light; telemetry and many monitors raise CPU.
A5: Disk | B5: 40 to 80 GB | C5: 80 GB | D5: 80 to 160 GB | E5: Guide says about 5 GB; extra is for the database and logs. Assumption.
A6: Database | B6: PostgreSQL in a container on the same server | C6: Managed PostgreSQL (optional) | D6: Managed PostgreSQL with backups | E6: A managed database gives backups and patching but costs about as much as the server.
A7: HTTPS | B7: Caddy + Let's Encrypt (no cost) | C7: Same | D7: Same, or the cloud load balancer | E7: Described in the Secure Deployment Guide.
A8: Region | B8: Any | C8: UK or EU | D8: UK (data residency) | E8: Public-sector users will normally want UK or EU residency.
A9: Not needed | B9: GPU, Ollama | C9: GPU, Ollama | D9: GPU, Ollama | E9: The deployment package leaves out the local language model.

Sheet Options
A1: Provider | B1: Service | C1: Plan / size | D1: vCPU | E1: RAM (GB) | F1: Storage | G1: Transfer included | H1: Price per month | I1: Currency | J1: Region / UK? | K1: Price status | L1: Reference (link to the price source) | M1: Notes
A2: DigitalOcean | B2: Droplet (virtual server) | C2: Basic, 4 GiB | D2: 2 | E2: 4 | F2: 80 GiB SSD | G2: 4,000 GiB | H2: 24 | I2: USD | J2: London (UK) data centre exists | K2: Verified on provider page | L2: https://www.digitalocean.com/pricing/droplets | M2: Plan availability per region not checked. Shared vCPU.
A3: DigitalOcean | B3: Droplet (virtual server) | C3: Basic, 8 GiB | D3: 4 | E3: 8 | F3: 160 GiB SSD | G3: 5,000 GiB | H3: 48 | I3: USD | J3: London (UK) data centre exists | K3: Verified on provider page | L3: https://www.digitalocean.com/pricing/droplets | M3: Headroom option for production.
A4: DigitalOcean | B4: Managed PostgreSQL | C4: 4 GiB / 2 vCPU | D4: 2 | E4: 4 | F4: 60 GB | H4: 60.9 | I4: USD | J4: UK region not checked | K4: Third-party: verify | L4: https://www.whtop.com/amp/plans/digitalocean.com/137775 | M4: Third-party listing (whtop); another source says 60.00. Managed databases are said to start at 15 USD; confirm on DigitalOcean.
A5: Amazon Web Services | B5: Lightsail instance (Linux) | C5: 4 GB bundle | D5: 2 | E5: 4 | F5: 80 GB SSD | G5: 4 TB | H5: 24 | I5: USD | J5: London region exists | K5: Verified on provider page | L5: https://aws.amazon.com/lightsail/pricing/ | M5: Includes public IPv4. IPv6-only version is 20 USD. London-specific price not separately checked.
A6: Amazon Web Services | B6: Lightsail instance (Linux) | C6: 8 GB bundle | D6: 2 | E6: 8 | F6: 160 GB SSD | G6: 5 TB | H6: 44 | I6: USD | J6: London region exists | K6: Verified on provider page | L6: https://aws.amazon.com/lightsail/pricing/ | M6: Only 2 vCPU at 8 GB.
A7: Amazon Web Services | B7: Lightsail managed database (standard) | C7: 2 GB | D7: 1 | E7: 2 | F7: 80 GB SSD | G7: 100 GB | H7: 30 | I7: USD | J7: London region exists | K7: Verified on provider page | L7: https://aws.amazon.com/lightsail/pricing/ | M7: Encrypted. High availability is a separate, higher-priced plan.
A8: Amazon Web Services | B8: Lightsail managed database (standard) | C8: 4 GB | D8: 2 | E8: 4 | F8: 120 GB SSD | G8: 100 GB | H8: 60 | I8: USD | J8: London region exists | K8: Verified on provider page | L8: https://aws.amazon.com/lightsail/pricing/ | M8: Encrypted.
A9: Microsoft Azure | B9: Virtual machine B2als v2 | C9: 2 vCPU, 4 GB | D9: 2 | E9: 4 | F9: Disk extra | G9: Extra | H9: 31.03 | I9: USD | J9: UK South | K9: Third-party: verify | L9: https://www.devzero.io/instances/azure/Standard_B2als_v2 | M9: Third-party site (devzero.io), about 0.0425 USD per hour. Another site shows a much lower rate, so the figure is unreliable. Use Azure's calculator, region UK South.
A10: Microsoft Azure | B10: Azure Database for PostgreSQL flexible server | C10: Burstable B2s, 2 vCPU, 4 GiB | D10: 2 | E10: 4 | F10: Storage extra | H10: 55 | I10: USD | J10: UK South | K10: Third-party: verify | L10: https://www.bytebase.com/dbcost/azure-flexible/instance/B2s/ | M10: Third-party site (bytebase.com), page updated 20 July 2026. Confirm in Azure's calculator.
A11: Hetzner | B11: Cloud server, Regular Performance | C11: CPX22 | D11: 2 | E11: 4 | F11: 80 GB NVMe | G11: 20 TB | H11: 19.99 | I11: EUR | J11: Germany / Finland (no UK) | K11: Verified on provider page | L11: https://www.hetzner.com/cloud/regular-performance/ | M11: Excl. VAT. Hetzner raised cloud prices in 2026, and its page showed the Create button as unavailable when checked on 27 Oct 2026; check availability before planning around it.
A12: Scaleway | B12: Instance (General Purpose) | C12: BASIC2-A2C-4G | D12: 2 | E12: 4 | F12: Block storage extra | G12: Egress included | H12: 16.79 | I12: EUR | J12: Paris (no UK) | K12: Verified on provider page | L12: https://www.scaleway.com/en/pricing/virtual-instances/ | M12: About EUR 0.023 per hour; excl. tax. Excludes storage and a public IPv4 address, which add cost.
A13: Mythic Beasts | B13: Virtual server | C13: Spec to confirm | I13: GBP | J13: UK: London (3 sites), Cambridge | K13: Quote needed | L13: https://www.mythic-beasts.com/servers/virtual | M13: Site shows 'from 4.90 GBP' (on demand 5.64), excl. VAT, but not for a 4 GB / 2 vCPU spec. Email sales@mythic-beasts.com for a quote. UK-owned provider.
A14: Render (platform as a service) | B14: Web service | C14: Standard, 1 vCPU / 2 GB | D14: 1 | E14: 2 | H14: 25 | I14: USD | J14: Not UK (check) | K14: Third-party: verify | L14: https://makerkit.dev/pricing-calculator/render | M14: Third-party figure. A platform service runs one container; ASTRA's three-part Compose stack would need re-packaging and a separate database, so this is not a like-for-like option.
A15: Fly.io (platform as a service) | B15: Machine | C15: shared-cpu-1x, 2 GB | D15: 1 | E15: 2 | H15: 10.7 | I15: USD | J15: Amsterdam example | K15: Third-party: verify | L15: https://www.morphllm.com/comparisons/flyio-vs-render | M15: Third-party figure; not a like-for-like option for the same reason as Render.
A16: University or customer infrastructure | B16: Existing virtual server | C16: As agreed with IT | E16: 4 | I16: GBP | J16: On site (UK) | K16: Quote needed | L16: No public price page: ask IT or the provider | M16: No public price. Cost is internal or recharged; a customer hosting it at their own expense (as proposed) falls here. Needs IT to provide a Docker host, HTTPS and backups.
A18: Green = read on the provider's own page on 27 Oct 2026. Amber = third-party site, verify. Red = no published price. Open the link in column L to check any figure.

Sheet Scenarios
A1: Monthly cost scenarios (edit the yellow cells)
A3: USD to GBP rate | B3: 0.75 | C3: PLACEHOLDER: enter today's rate
A4: EUR to GBP rate | B4: 0.85 | C4: PLACEHOLDER: enter today's rate
A5: UK VAT rate | B5: 0.2 | C5: Prices are quoted excl. VAT; set 0 if VAT-exempt or recoverable
A7: Scenario | B7: Provider cost (as quoted) | C7: Currency | D7: Monthly in GBP excl. VAT | E7: Monthly in GBP incl. VAT | F7: Per year incl. VAT (GBP) | G7: What is included | H7: Reference (Options sheet rows and link)
A8: 1. Shared test: DigitalOcean 4 GiB droplet, database in a container | B8: =Options!H2 | C8: USD | D8: =B8*IF(C8="USD",$B$3,IF(C8="EUR",$B$4,1)) | E8: =D8*(1+$B$5) | F8: =E8*12 | G8: One server running the whole stack; HTTPS with Caddy (free). No managed backups. | H8: Options row 2: https://www.digitalocean.com/pricing/droplets
A9: 1. Shared test: Amazon Lightsail 4 GB, database in a container | B9: =Options!H5 | C9: USD | D9: =B9*IF(C9="USD",$B$3,IF(C9="EUR",$B$4,1)) | E9: =D9*(1+$B$5) | F9: =E9*12 | G9: As above. | H9: Options row 5: https://aws.amazon.com/lightsail/pricing/
A10: 1. Shared test: Scaleway BASIC2-A2C-4G, database in a container | B10: =Options!H12 | C10: EUR | D10: =B10*IF(C10="USD",$B$3,IF(C10="EUR",$B$4,1)) | E10: =D10*(1+$B$5) | F10: =E10*12 | G10: As above; storage and IPv4 extra, so slightly higher. | H10: Options row 12: https://www.scaleway.com/en/pricing/virtual-instances/
A11: 1. Shared test: Hetzner CPX22, database in a container | B11: =Options!H11 | C11: EUR | D11: =B11*IF(C11="USD",$B$3,IF(C11="EUR",$B$4,1)) | E11: =D11*(1+$B$5) | F11: =E11*12 | G11: As above; availability to be checked. | H11: Options row 11: https://www.hetzner.com/cloud/regular-performance/
A12: 2. Pilot: Lightsail 4 GB server + Lightsail 2 GB managed database | B12: =Options!H5+Options!H7 | C12: USD | D12: =B12*IF(C12="USD",$B$3,IF(C12="EUR",$B$4,1)) | E12: =D12*(1+$B$5) | F12: =E12*12 | G12: Managed, encrypted database with provider backups; server patched by you. | H12: Options rows 5 and 7: https://aws.amazon.com/lightsail/pricing/
A13: 2. Pilot: DigitalOcean 4 GiB droplet + managed PostgreSQL 4 GiB | B13: =Options!H2+Options!H4 | C13: USD | D13: =B13*IF(C13="USD",$B$3,IF(C13="EUR",$B$4,1)) | E13: =D13*(1+$B$5) | F13: =E13*12 | G13: Database figure is third-party; verify. | H13: Options rows 2 and 4: https://www.digitalocean.com/pricing/droplets and https://www.whtop.com/amp/plans/digitalocean.com/137775 (database, third party)
A14: 2. Pilot: Azure B2als v2 VM + PostgreSQL B2s (UK South) | B14: =Options!H9+Options!H10 | C14: USD | D14: =B14*IF(C14="USD",$B$3,IF(C14="EUR",$B$4,1)) | E14: =D14*(1+$B$5) | F14: =E14*12 | G14: Both figures are third-party; verify in Azure's calculator. Storage and bandwidth extra. | H14: Options rows 9 and 10: https://www.devzero.io/instances/azure/Standard_B2als_v2 and https://www.bytebase.com/dbcost/azure-flexible/instance/B2s/ (both third party)
A15: 3. Small production: DigitalOcean 8 GiB droplet + managed PostgreSQL 4 GiB | B15: =Options!H3+Options!H4 | C15: USD | D15: =B15*IF(C15="USD",$B$3,IF(C15="EUR",$B$4,1)) | E15: =D15*(1+$B$5) | F15: =E15*12 | G15: Excludes staging server, load balancer, backups beyond the provider's, monitoring. | H15: Options rows 3 and 4: https://www.digitalocean.com/pricing/droplets and https://www.whtop.com/amp/plans/digitalocean.com/137775 (database, third party)
A16: 3. Small production: Lightsail 8 GB server + 4 GB managed database | B16: =Options!H6+Options!H8 | C16: USD | D16: =B16*IF(C16="USD",$B$3,IF(C16="EUR",$B$4,1)) | E16: =D16*(1+$B$5) | F16: =E16*12 | G16: As above. | H16: Options rows 6 and 8: https://aws.amazon.com/lightsail/pricing/
A18: Monthly totals include only the rows listed. They exclude domain, backups storage, extra traffic, monitoring and staff time (see Other costs).

Sheet Other costs
A1: Item | B1: Typical cost | C1: Status | D1: Notes | E1: Reference
A2: HTTPS certificate | B2: 0 (Let's Encrypt via Caddy) | C2: Known | D2: Free and renewed automatically by Caddy; a cloud load balancer's managed certificate is also free but the load balancer itself is billed. | E2: https://letsencrypt.org/about/
A3: Domain name | B3: Roughly 10 to 15 GBP a year for a common domain | C3: Estimate: verify | D3: Varies by registrar and domain type; a university or customer may supply a subdomain at no cost. | E3: No source: rough estimate, check a registrar
A4: Backups | B4: Provider snapshots or object storage, billed by size | C4: Not priced | D4: Managed databases include backups; for a self-run database copy a pg_dump off the server and test the restore. | E4: No source: depends on provider
A5: Outbound traffic beyond the allowance | B5: Provider-specific per GB | C5: Not priced | D5: Allowances in the Options sheet are large (several TB) for a few users and SDK feeds. | E5: Provider pricing pages (see Options)
A6: Monitoring and log storage | B6: Free to low for a small site | C6: Not priced | D6: Send logs and the audit log to the organisation's existing logging if there is one. | E6: No source
A7: Staff time | B7: Hours per month | C7: Not priced | D7: Patching, updates, backup checks; the main real cost for a self-hosted option. A managed database removes part of it. | E7: No source: staff time
A8: Independent security test | B8: Quote needed | C8: Not priced | D8: Recommended before a regulated customer goes live. | E8: No source: ask for quotes
A9: Single sign-on with MFA in front | B9: Depends on the organisation's identity provider | C9: Not priced | D9: Many organisations already have this through Entra ID or similar. | E9: No source: depends on the organisation

Sheet Sources
A1: Provider / topic | B1: URL | C1: How used
A2: DigitalOcean droplets | B2: https://www.digitalocean.com/pricing/droplets | C2: Droplet prices read on 27 Oct 2026
A3: Amazon Lightsail | B3: https://aws.amazon.com/lightsail/pricing/ | C3: Instance and managed database prices read on 27 Oct 2026
A4: Hetzner Cloud | B4: https://www.hetzner.com/cloud/regular-performance/ | C4: CPX22 price and 'currently unavailable' notice read on 27 Oct 2026
A5: Scaleway | B5: https://www.scaleway.com/en/pricing/virtual-instances/ | C5: BASIC2-A2C-4G price read on 27 Oct 2026
A6: Mythic Beasts | B6: https://www.mythic-beasts.com/servers/virtual | C6: UK locations and 'from' price; quote needed
A7: DigitalOcean managed PostgreSQL (third party) | B7: https://www.whtop.com/amp/plans/digitalocean.com/137775 | C7: Indicative price; verify
A8: Azure VM B2als v2 (third party) | B8: https://www.devzero.io/instances/azure/Standard_B2als_v2 | C8: Indicative price; verify
A9: Azure PostgreSQL B2s (third party) | B9: https://www.bytebase.com/dbcost/azure-flexible/instance/B2s/ | C9: Indicative price; verify
A10: Render pricing (third party) | B10: https://makerkit.dev/pricing-calculator/render | C10: Indicative price
A11: Fly.io vs Render (third party) | B11: https://www.morphllm.com/comparisons/flyio-vs-render | C11: Indicative price
A12: Hetzner 2026 price changes (third party) | B12: https://privatedevops.com/news/hetzner-june-2026-cloud-price-increase-what-to-do | C12: Context for the Hetzner repricing
A13: ASTRA hosting requirements | B13: deploy/DEPLOY.md in the ASTRA repository | C13: RAM, disk and Docker requirements
